synthizer_fx/__init__.py
synthizer_fx/main.py
synthizer_fx/reverb.py
synthizer_fx/gui/__init__.py
synthizer_fx/gui/numeric_ctrl.py
synthizer_fx/gui/reverb.py
synthizer_fx/gui/setting.py
synthizer_fx-2021.0.0.dist-info/AUTHORS
synthizer_fx-2021.0.0.dist-info/LICENSE
synthizer_fx-2021.0.0.dist-info/METADATA
synthizer_fx-2021.0.0.dist-info/WHEEL
synthizer_fx-2021.0.0.dist-info/entry_points.txt
synthizer_fx-2021.0.0.dist-info/pbr.json
synthizer_fx-2021.0.0.dist-info/top_level.txt
synthizer_fx-2021.0.0.dist-info/RECORD
