Metadata-Version: 2.1
Name: synthizer-fx
Version: 2021.0.0
Summary: Tools for working with Synthizer's effects
Home-page: http://synthizer_fx.readthedocs.io/
Author: Chris Norman
Author-email: chris.norman2@googlemail.com
License: MPL
Platform: UNKNOWN
Requires-Dist: synthizer
Requires-Dist: pyyaml
